ibtrade/BarConverter.py
ibtrade/Configurator.py
ibtrade/DBConnectionProfile.py
ibtrade/DataSource.py
ibtrade/DualExpAvgIndicator.py
ibtrade/Exchange.py
ibtrade/IBCallback.py
ibtrade/IBClient.py
ibtrade/IBOrderFactory.py
ibtrade/MACDIndicator.py
ibtrade/MathUtilities.py
ibtrade/OhlcBar.py
ibtrade/Simulation.py
ibtrade/Singleton.py
ibtrade/Strategy.py
ibtrade/TransactionAgent.py
ibtrade/__about__.py
ibtrade/__init__.py
ibtrade/orders.py
ibtrade/tests/__init__.py
ibtrade/tests/test_realtime_data.py
ibtrade-0.1.2.dist-info/METADATA
ibtrade-0.1.2.dist-info/WHEEL
ibtrade-0.1.2.dist-info/licenses/LICENSE
ibtrade-0.1.2.dist-info/RECORD
