Metadata-Version: 2.4
Name: ibtrade
Version: 0.1.2
Summary: Tools built on Interactive Broker's API
Project-URL: Documentation, https://github.com/mathtix/ibtrade#readme
Project-URL: Issues, https://github.com/mathtix/ibtrade/issues
Project-URL: Source, https://github.com/mathtix/ibtrade
Author-email: Doug Service <doug@mathtix.com>
License-Expression: MIT
License-File: LICENSE
Keywords: Interactive Brokers,finance
Classifier: Development Status :: 4 - Beta
Classifier: Intended Audience :: Developers
Classifier: License :: OSI Approved :: MIT License
Classifier: Programming Language :: Python
Classifier: Programming Language :: Python :: 3.13
Classifier: Programming Language :: Python :: Implementation :: CPython
Classifier: Topic :: Software Development :: Libraries
Classifier: Topic :: Utilities
Requires-Python: >=3.13
